LICENCE
MANIFEST.in
README.md
pyproject.toml
setup.py
src/bayesbay/__init__.py
src/bayesbay/_bayes_inversion.py
src/bayesbay/_markov_chain.py
src/bayesbay/_state.py
src/bayesbay/_utils.py
src/bayesbay/_utils_1d.cpp
src/bayesbay/_utils_1d.pyx
src/bayesbay/_version.py
src/bayesbay.egg-info/PKG-INFO
src/bayesbay.egg-info/SOURCES.txt
src/bayesbay.egg-info/dependency_links.txt
src/bayesbay.egg-info/requires.txt
src/bayesbay.egg-info/top_level.txt
src/bayesbay/discretization/__init__.py
src/bayesbay/discretization/_discretization.py
src/bayesbay/discretization/_voronoi.py
src/bayesbay/exceptions/__init__.py
src/bayesbay/exceptions/_exceptions.py
src/bayesbay/likelihood/__init__.py
src/bayesbay/likelihood/_log_likelihood.py
src/bayesbay/likelihood/_target.py
src/bayesbay/parameterization/__init__.py
src/bayesbay/parameterization/_parameter_space.py
src/bayesbay/parameterization/_parameterization.py
src/bayesbay/perturbations/__init__.py
src/bayesbay/perturbations/_base_perturbation.py
src/bayesbay/perturbations/_birth_death.py
src/bayesbay/perturbations/_data_noise.py
src/bayesbay/perturbations/_param_space.py
src/bayesbay/perturbations/_param_values.py
src/bayesbay/prior/__init__.py
src/bayesbay/prior/_prior.py
src/bayesbay/samplers/__init__.py
src/bayesbay/samplers/_samplers.py