Metadata-Version: 2.1
Name: bayesbay
Version: 0.3.4
Summary: UNKNOWN
Home-page: UNKNOWN
License: UNKNOWN
Platform: UNKNOWN
License-File: LICENCE
